{
  "Meta, USA": {
    "display_name": "Meta, USA",
    "cited_artifacts": [
      {
        "title": "Seastar: Vertex-Centric Programming for Graph Neural Networks",
        "conference": "EUROSYS",
        "year": 2021,
        "citations": 52,
        "authors": [
          "Yidi Wu 0001"
        ]
      }
    ],
    "total_citations": 52,
    "member_count": 0
  },
  "Chinese University of Hong Kong": {
    "display_name": "Chinese University of Hong Kong",
    "cited_artifacts": [
      {
        "title": "Seastar: Vertex-Centric Programming for Graph Neural Networks",
        "conference": "EUROSYS",
        "year": 2021,
        "citations": 52,
        "authors": [
          "Boyang Li 0016"
        ]
      }
    ],
    "total_citations": 52,
    "member_count": 0
  },
  "Stony Brook University": {
    "display_name": "Stony Brook University",
    "cited_artifacts": [
      {
        "title": "BetrFS: A Compleat File System for Commodity SSDs",
        "conference": "EUROSYS",
        "year": 2022,
        "citations": 1,
        "authors": [
          "Michael A. Bender"
        ]
      },
      {
        "title": "Back-Propagating System Dependency Impact for Attack Investigation",
        "conference": "USENIXSEC",
        "year": 2022,
        "citations": 17,
        "authors": [
          "Ting Wang 0006"
        ]
      }
    ],
    "total_citations": 18,
    "member_count": 0
  },
  "Virginia Tech, Department of Computer Science, Blacksburg, VA, USA": {
    "display_name": "Virginia Tech, Department of Computer Science, Blacksburg, VA, USA",
    "cited_artifacts": [
      {
        "title": "Back-Propagating System Dependency Impact for Attack Investigation",
        "conference": "USENIXSEC",
        "year": 2022,
        "citations": 17,
        "authors": [
          "Peng Gao 0008"
        ]
      }
    ],
    "total_citations": 17,
    "member_count": 0
  },
  "Case Western Reserve University": {
    "display_name": "Case Western Reserve University",
    "cited_artifacts": [
      {
        "title": "Back-Propagating System Dependency Impact for Attack Investigation",
        "conference": "USENIXSEC",
        "year": 2022,
        "citations": 17,
        "authors": [
          "Erman Ayday"
        ]
      }
    ],
    "total_citations": 17,
    "member_count": 0
  },
  "Washington State University": {
    "display_name": "Washington State University",
    "cited_artifacts": [
      {
        "title": "PolyFuzz: Holistic Greybox Fuzzing of Multi-Language Systems",
        "conference": "USENIXSEC",
        "year": 2023,
        "citations": 8,
        "authors": [
          "Wen Li 0007"
        ]
      }
    ],
    "total_citations": 8,
    "member_count": 0
  },
  "Clemson University": {
    "display_name": "Clemson University",
    "cited_artifacts": [
      {
        "title": "PolyFuzz: Holistic Greybox Fuzzing of Multi-Language Systems",
        "conference": "USENIXSEC",
        "year": 2023,
        "citations": 8,
        "authors": [
          "Long Cheng 0005"
        ]
      }
    ],
    "total_citations": 8,
    "member_count": 0
  },
  "Hong Kong Polytechnic University": {
    "display_name": "Hong Kong Polytechnic University",
    "cited_artifacts": [
      {
        "title": "PolyFuzz: Holistic Greybox Fuzzing of Multi-Language Systems",
        "conference": "USENIXSEC",
        "year": 2023,
        "citations": 8,
        "authors": [
          "Xiapu Luo"
        ]
      }
    ],
    "total_citations": 8,
    "member_count": 0
  },
  "University at Buffalo": {
    "display_name": "University at Buffalo",
    "cited_artifacts": [
      {
        "title": "PolyFuzz: Holistic Greybox Fuzzing of Multi-Language Systems",
        "conference": "USENIXSEC",
        "year": 2023,
        "citations": 8,
        "authors": [
          "Haipeng Cai"
        ]
      }
    ],
    "total_citations": 8,
    "member_count": 0
  },
  "University of Maryland": {
    "display_name": "University of Maryland",
    "cited_artifacts": [
      {
        "title": "GET /out: Automated Discovery of Application-Layer Censorship Evasion Strategies",
        "conference": "USENIXSEC",
        "year": 2022,
        "citations": 4,
        "authors": [
          "Kevin Bock 0001"
        ]
      },
      {
        "title": "Your Censor is My Censor: Weaponizing Censorship Infrastructure for Availability Attacks",
        "conference": "WOOT",
        "year": 2021,
        "citations": 2,
        "authors": [
          "Kevin Bock 0001"
        ]
      }
    ],
    "total_citations": 6,
    "member_count": 0
  },
  "Indraprastha Institute of Information Technology, Delhi": {
    "display_name": "Indraprastha Institute of Information Technology, Delhi",
    "cited_artifacts": [
      {
        "title": "TileClipper: Lightweight Selection of Regions of Interest from Videos for Traffic Surveillance",
        "conference": "ATC",
        "year": 2024,
        "citations": 1,
        "authors": [
          "Shubham Chaudhary 0006"
        ]
      }
    ],
    "total_citations": 1,
    "member_count": 0
  },
  "Cornell University": {
    "display_name": "Cornell University",
    "cited_artifacts": [
      {
        "title": "BetrFS: A Compleat File System for Commodity SSDs",
        "conference": "EUROSYS",
        "year": 2022,
        "citations": 1,
        "authors": [
          "Alex Conway 0001"
        ]
      }
    ],
    "total_citations": 1,
    "member_count": 0
  },
  "New York University": {
    "display_name": "New York University",
    "cited_artifacts": [
      {
        "title": "BetrFS: A Compleat File System for Commodity SSDs",
        "conference": "EUROSYS",
        "year": 2022,
        "citations": 1,
        "authors": [
          "Martin Farach-Colton"
        ]
      }
    ],
    "total_citations": 1,
    "member_count": 0
  },
  "VMware Research, Palo Alto, CA, USA": {
    "display_name": "VMware Research, Palo Alto, CA, USA",
    "cited_artifacts": [
      {
        "title": "BetrFS: A Compleat File System for Commodity SSDs",
        "conference": "EUROSYS",
        "year": 2022,
        "citations": 1,
        "authors": [
          "Rob Johnson 0001"
        ]
      }
    ],
    "total_citations": 1,
    "member_count": 0
  },
  "University of North Carolina at Chapel Hill": {
    "display_name": "University of North Carolina at Chapel Hill",
    "cited_artifacts": [
      {
        "title": "BetrFS: A Compleat File System for Commodity SSDs",
        "conference": "EUROSYS",
        "year": 2022,
        "citations": 1,
        "authors": [
          "Donald E. Porter"
        ]
      }
    ],
    "total_citations": 1,
    "member_count": 0
  },
  "Technical University of Munich, Germany": {
    "display_name": "Technical University of Munich, Germany",
    "cited_artifacts": [
      {
        "title": "VMSH: Hypervisor-agnostic Guest Overlays for VMs",
        "conference": "EUROSYS",
        "year": 2022,
        "citations": 1,
        "authors": [
          "Pramod Bhatotia"
        ]
      }
    ],
    "total_citations": 1,
    "member_count": 0
  },
  "Ain Shams University": {
    "display_name": "Ain Shams University",
    "cited_artifacts": [
      {
        "title": "REFL: Resource-Efficient Federated Learning",
        "conference": "EUROSYS",
        "year": 2023,
        "citations": 1,
        "authors": [
          "Ahmed M. Abdelmoniem"
        ]
      }
    ],
    "total_citations": 1,
    "member_count": 0
  },
  "Hong Kong University of Science and Technology": {
    "display_name": "Hong Kong University of Science and Technology",
    "cited_artifacts": [
      {
        "title": "From Purity to Peril: Backdooring Merged Models From \"Harmless\" Benign Components",
        "conference": "USENIXSEC",
        "year": 2025,
        "citations": 1,
        "authors": [
          "Xinlei He 0001"
        ]
      }
    ],
    "total_citations": 1,
    "member_count": 0
  },
  "Fujian Normal University": {
    "display_name": "Fujian Normal University",
    "cited_artifacts": [
      {
        "title": "From Purity to Peril: Backdooring Merged Models From \"Harmless\" Benign Components",
        "conference": "USENIXSEC",
        "year": 2025,
        "citations": 1,
        "authors": [
          "Xinyi Huang 0001"
        ]
      }
    ],
    "total_citations": 1,
    "member_count": 0
  }
}